huayi_mcp_server/__init__.py
huayi_mcp_server/__main__.py
huayi_mcp_server/server.py
huayi_mcp_server/tools.py
huayi_mcp_server/sdk/__init__.py
huayi_mcp_server/sdk/huajitong.py
huayi_mcp_server/sdk/models.py
huayi_mcp_server/sdk/sign.py
huayi_mcp-0.1.10.dist-info/METADATA
huayi_mcp-0.1.10.dist-info/WHEEL
huayi_mcp-0.1.10.dist-info/entry_points.txt
huayi_mcp-0.1.10.dist-info/RECORD
