Metadata-Version: 2.4
Name: huayi-mcp
Version: 0.1.10
Summary: Huayi MCP Servers
Author: Chen Zhongrun
Requires-Python: >=3.13.0
Requires-Dist: anyio>=4.5
Requires-Dist: click>=8.2.0
Requires-Dist: hatchling>=1.28.0
Requires-Dist: httpx>=0.27
Requires-Dist: mcp
Requires-Dist: starlette
Requires-Dist: uvicorn
